pdf_reactor/__init__.py
pdf_reactor/apps.py
pdf_reactor/consumers.py
pdf_reactor/settings.py
django_pdf_reactor-0.1.3.dist-info/LICENSE
django_pdf_reactor-0.1.3.dist-info/WHEEL
django_pdf_reactor-0.1.3.dist-info/METADATA
django_pdf_reactor-0.1.3.dist-info/RECORD
