Metadata-Version: 2.1
Name: django-pdf-reactor
Version: 0.1.3
Summary: PDF generator for Django, support for async generation in Django Channels worker or with Django 3.1 async views.
Home-page: https://github.com/terminalkitten/django-pdf-reactor
License: MIT
Author: TK
Author-email: dk@terminalkitten.com
Requires-Python: >=3.7,<4.0
Classifier: License :: OSI Approved :: MIT License
Classifier: Programming Language :: Python :: 3
Classifier: Programming Language :: Python :: 3.7
Classifier: Programming Language :: Python :: 3.8
Requires-Dist: Django (>=3.1,<4.0)
Requires-Dist: channels (>=2.4.0,<3.0.0)
Requires-Dist: channels-redis (>=3.0.1,<4.0.0)
Requires-Dist: django-channels-graphql-ws (>=0.7.4,<0.8.0)
Requires-Dist: nanoid (>=2.0.0,<3.0.0)
Requires-Dist: nest_asyncio (>=1.4.3,<2.0.0)
Requires-Dist: pdfmate (>=0.4.9,<0.5.0)
Requires-Dist: pdoc (>=0.3.2,<0.4.0)
Project-URL: Repository, https://github.com/terminalkitten/django-pdf-reactor
